dimans/__init__.py
dimans/base_classes.py
dimans/constants.py
dimans/dimension.py
dimans/cli/__init__.py
dimans/cli/__main__.py
dimans/cli/cli.lark
dimans/cli/parser.py
dimans/cli/style/app.tcss
dimans/cli/style/debugger.tcss
dimans/units/__init__.py
dimans/units/metric_utils.py
dimans/units/si.py
dimans/units/common/__init__.py
dimans/units/common/angle.py
dimans/units/common/energy.py
dimans/units/common/length.py
dimans/units/common/mass.py
dimans/units/common/radioactivity.py
dimans/units/common/time.py
dimans/units/imperial/__init__.py
dimans/units/imperial/area.py
dimans/units/imperial/length.py
dimans/units/imperial/mass.py
dimans/units/imperial/volume.py
dimans/units/metric/__init__.py
dimans/units/metric/angstrom.py
dimans/units/metric/bit.py
dimans/units/metric/byte.py
dimans/units/metric/calorie.py
dimans/units/metric/electron_volt.py
dimans/units/metric/litre.py
dimans/units/metric/parsec.py
dimans/units/si_base/__init__.py
dimans/units/si_base/ampere.py
dimans/units/si_base/candela.py
dimans/units/si_base/gram.py
dimans/units/si_base/kelvin.py
dimans/units/si_base/metre.py
dimans/units/si_base/mole.py
dimans/units/si_base/second.py
dimans/units/si_derived/__init__.py
dimans/units/si_derived/becquerel.py
dimans/units/si_derived/celsius.py
dimans/units/si_derived/coulomb.py
dimans/units/si_derived/farad.py
dimans/units/si_derived/gray.py
dimans/units/si_derived/henry.py
dimans/units/si_derived/hertz.py
dimans/units/si_derived/joule.py
dimans/units/si_derived/katal.py
dimans/units/si_derived/lumen.py
dimans/units/si_derived/lux.py
dimans/units/si_derived/newton.py
dimans/units/si_derived/ohm.py
dimans/units/si_derived/pascal.py
dimans/units/si_derived/radian.py
dimans/units/si_derived/siemens.py
dimans/units/si_derived/sievert.py
dimans/units/si_derived/steradian.py
dimans/units/si_derived/tesla.py
dimans/units/si_derived/volt.py
dimans/units/si_derived/watt.py
dimans/units/si_derived/weber.py
dimans/units/unusual/__init__.py
dimans/units/unusual/angle.py
dimans-0.0.24.dist-info/entry_points.txt
dimans-0.0.24.dist-info/LICENSE
dimans-0.0.24.dist-info/WHEEL
dimans-0.0.24.dist-info/METADATA
dimans-0.0.24.dist-info/RECORD
