Metadata-Version: 2.1
Name: dimans
Version: 0.0.24
Summary: Dimensional analysis and unit conversion library
Keywords: units,calculation,calculator,constants
Author-email: Emre Özcan <emre@emreis.com>
Maintainer-email: Emre Özcan <emre@emreis.com>
Requires-Python: >=3.10
Classifier: Development Status :: 3 - Alpha
Classifier: Environment :: Console
Classifier: Intended Audience :: Developers
Classifier: Intended Audience :: Education
Classifier: Intended Audience :: Science/Research
Classifier: License :: OSI Approved :: MIT License
Classifier: Operating System :: OS Independent
Classifier: Programming Language :: Python
Classifier: Programming Language :: Python :: 3.10
Classifier: Programming Language :: Python :: 3.11
Classifier: Programming Language :: Python :: 3.12
Classifier: Topic :: Scientific/Engineering
Classifier: Topic :: Utilities
Requires-Dist: lark ; extra == "cli"
Requires-Dist: rich ; extra == "cli"
Requires-Dist: textual ; extra == "cli"
Project-URL: Issues, https://github.com/emreozcan/dimans/issues
Project-URL: Repository, https://github.com/emreozcan/dimans
Provides-Extra: cli
